hive/__init__.py
hive/exceptions.py
hive/executor.py
hive_executor_py-1.0.9.dev1.dist-info/DESCRIPTION.rst
hive_executor_py-1.0.9.dev1.dist-info/METADATA
hive_executor_py-1.0.9.dev1.dist-info/RECORD
hive_executor_py-1.0.9.dev1.dist-info/WHEEL
hive_executor_py-1.0.9.dev1.dist-info/metadata.json
hive_executor_py-1.0.9.dev1.dist-info/top_level.txt
